MatPlus/BarPlot.py
MatPlus/BoxPlot.py
MatPlus/Histogram.py
MatPlus/LinePlot.py
MatPlus/ScatterPlot.py
MatPlus/StemPlot.py
MatPlus/__init__.py
matplus-0.2.1.dist-info/licenses/AUTHORS
matplus-0.2.1.dist-info/licenses/LICENSE
tests/__init__.py
tests/test_BarPlot.py
tests/test_BoxPlot.py
tests/test_Histogram.py
tests/test_LinePlot.py
tests/test_ScatterPlot.py
tests/test_StemPlot.py
matplus-0.2.1.dist-info/METADATA
matplus-0.2.1.dist-info/WHEEL
matplus-0.2.1.dist-info/top_level.txt
matplus-0.2.1.dist-info/RECORD
