Metadata-Version: 2.4
Name: MatPlus
Version: 0.2.1
Summary: This package is for easy, convenient plotting in Python.
Home-page: https://github.com/ac-i2i-engineering/MatPlus
Author: Dhyey Mavani, Liam Davis, Ryan Ji, Surya Rao, Weixin Lin
License: MIT
Keywords: Plotting Python Matplotlib
Classifier: Programming Language :: Cython
Classifier: Programming Language :: Python
Classifier: Programming Language :: Python :: 3
Classifier: License :: OSI Approved :: MIT License
Classifier: Operating System :: OS Independent
Requires-Python: >=3.8
License-File: LICENSE
License-File: AUTHORS
Requires-Dist: matplotlib
Requires-Dist: numpy
Requires-Dist: pandas
Dynamic: author
Dynamic: classifier
Dynamic: description
Dynamic: description-content-type
Dynamic: home-page
Dynamic: keywords
Dynamic: license
Dynamic: license-file
Dynamic: requires-dist
Dynamic: requires-python
Dynamic: summary
